contextualize/__init__.py
contextualize/cli.py
contextualize/external.py
contextualize/payload.py
contextualize/reference.py
contextualize/repomap.py
contextualize/shell.py
contextualize/tokenize.py
contextualize/utils.py
contextualize-0.1.0.dist-info/METADATA
contextualize-0.1.0.dist-info/WHEEL
contextualize-0.1.0.dist-info/entry_points.txt
contextualize-0.1.0.dist-info/top_level.txt
contextualize-0.1.0.dist-info/RECORD
