Metadata-Version: 2.4
Name: contextualize
Version: 0.1.0
Summary: LLM prompt/context preparation utility
Author: jmpaz
Project-URL: Homepage, https://github.com/jmpaz/contextualize
Requires-Python: >=3.6
Requires-Dist: pyyaml
Requires-Dist: pathspec
Requires-Dist: aider-chat>=0.83.2
Requires-Dist: anthropic==0.42.0
Requires-Dist: pyperclip>=1.8.2
Requires-Dist: tiktoken>=0.6.0
